digsec/__init__.py
digsec/algorithms.py
digsec/answer.py
digsec/comm.py
digsec/constants.py
digsec/download.py
digsec/help.py
digsec/messages.py
digsec/query.py
digsec/scripts.py
digsec/utils.py
digsec/validate.py
digsec-0.2.dist-info/METADATA
digsec-0.2.dist-info/RECORD
digsec-0.2.dist-info/WHEEL
digsec-0.2.dist-info/entry_points.txt
digsec-0.2.dist-info/top_level.txt
