Metadata-Version: 2.1
Name: digsec
Version: 0.2
Summary: dig like command line utility to understand DNSSEC
Home-page: https://github.com/metebalci/digsec
Author: Mete Balci
Author-email: metebalci@gmail.com
License: GPLv3
Keywords: DNSSEC
Platform: UNKNOWN
Classifier: Development Status :: 3 - Alpha
Classifier: Environment :: Console
Classifier: Intended Audience :: Information Technology
Classifier: License :: OSI Approved :: GNU General Public License v3 (GPLv3)
Classifier: Natural Language :: English
Classifier: Operating System :: OS Independent
Classifier: Programming Language :: Python :: 3 :: Only
Classifier: Topic :: Internet :: Name Service (DNS)
Classifier: Topic :: System :: Networking
Classifier: Topic :: System :: Systems Administration
Classifier: Topic :: Utilities
Requires-Dist: rsa
